django_hashable_file_fields/__init__.py
django_hashable_file_fields/hashers.py
django_hashable_file_fields/models.py
django_hashable_file_fields-1.2.1.dist-info/METADATA
django_hashable_file_fields-1.2.1.dist-info/WHEEL
django_hashable_file_fields-1.2.1.dist-info/RECORD
